{
  "tarih": "2026-06-10",
  "gun": "Çarşamba",
  "saat": "18:00",
  "ay_label": "Haziran 2026",
  "hizmet_anahtari": "ai_reklam",
  "hizmet": "Yapay Zeka Reklam Filmleri",
  "layout": "M",
  "service_no": 2,
  "headline": null,
  "subtitle": null,
  "slogan": "GELECEĞİN HİKÂYELERİNİ YAZIYORUZ",
  "subslogan": "Yapay zeka ile reklam filminde devrim.",
  "cta_headline": null,
  "cta_body": null,
  "caption": "✨ Yapay zeka destekli reklam filmleriyle sınırları zorlayın. Vizyoner yaklaşımımızla, markanızı ileri taşıyoruz. Siz de bu sinematik devrimin parçası olun. \n\n📞 İletişim:\n🌐 www.saturnfilm.net\n📩 info@saturnfilm.net\n#YapayZeka #AIReklam #AIVideo #ReklamFilmi #GenerativeAI #SaturnFilm #SaturnFilmEntertainment",
  "dosya": "2026-06-10-yapay-zeka-reklam-filmleri-M.png",
  "image_url": "https://raw.githubusercontent.com/burakvarlik/saturn-film-social-media/main/posts/2026-06-10-yapay-zeka-reklam-filmleri-M.png",
  "olusturma_tarihi": "2026-06-05T18:13:16.927686+00:00",
  "durum": "pending"
}